TileScraper-0.1.0.dist-info/DESCRIPTION.rst
TileScraper-0.1.0.dist-info/METADATA
TileScraper-0.1.0.dist-info/RECORD
TileScraper-0.1.0.dist-info/WHEEL
TileScraper-0.1.0.dist-info/metadata.json
TileScraper-0.1.0.dist-info/top_level.txt
tilescraper/__init__.py
tilescraper/tilescraper.py
