Metadata-Version: 2.0
Name: TileScraper
Version: 0.1.0
Summary: This module pulls a panel of tile-composite images from MODIS satellites given latitude and longitude of the edges plus start and end dates.
Home-page: http://www.github.com/tavisbarr/tilescraper
Author: Tavis Barr
Author-email: tavisbarr@gmail.com
License: UNKNOWN
Platform: UNKNOWN
